MANIFEST.in
README.rst
setup.cfg
setup.py
checkio/__init__.py
checkio.egg-info/PKG-INFO
checkio.egg-info/SOURCES.txt
checkio.egg-info/dependency_links.txt
checkio.egg-info/top_level.txt
checkio/ELEMENTARY/__init__.py
checkio/ELEMENTARY/absolute-sorting.py
checkio/ELEMENTARY/binary-count.py
checkio/ELEMENTARY/boolean-algebra.py
checkio/ELEMENTARY/building-base.py
checkio/ELEMENTARY/common-words.py
checkio/ELEMENTARY/count-inversions.py
checkio/ELEMENTARY/days-diff.py
checkio/ELEMENTARY/digits-multiplication.py
checkio/ELEMENTARY/end-of-other.py
checkio/ELEMENTARY/even-last.py
checkio/ELEMENTARY/fizz-buzz.py
checkio/ELEMENTARY/friends.py
checkio/ELEMENTARY/i-love-python.py
checkio/ELEMENTARY/index-power.py
checkio/ELEMENTARY/monkey-typing.py
checkio/ELEMENTARY/most-numbers.py
checkio/ELEMENTARY/number-radix.py
checkio/ELEMENTARY/pangram.py
checkio/ELEMENTARY/right-to-left.py
checkio/ELEMENTARY/secret-message.py
checkio/ELEMENTARY/three-words.py
checkio/HOME/__init__.py
checkio/HOME/break-rings.py
checkio/HOME/count-neighbours.py
checkio/HOME/find-friends.py
checkio/HOME/flatten-dict.py
checkio/HOME/golden-pyramid.py
checkio/HOME/house-password.py
checkio/HOME/median.py
checkio/HOME/min-max.py
checkio/HOME/most-wanted-letter.py
checkio/HOME/non-unique-elements.py
checkio/HOME/open-labyrinth.py
checkio/HOME/pawn-brotherhood.py
checkio/HOME/prime-palindrome-golf.py
checkio/HOME/roman-numerals.py
checkio/HOME/solution-for-anything.py
checkio/HOME/speechmodule.py
checkio/HOME/the-best-number-ever.py
checkio/HOME/x-o-referee.py
checkio/Lib/__init__.py
checkio/Lib/graph.py
checkio/Lib/roman.py