Metadata-Version: 1.1
Name: checkio
Version: 2.0
Summary: checkio solution
Home-page: http://github.com/ifooth/checkio
Author: Joe Lei
Author-email: thezero12@hotmail.com
License: IFOOTH
Keywords: checkio
Platform: UNKNOWN
Classifier: Programming Language :: Python
